wikipedia/__init__.py
wikipedia/exceptions.py
wikipedia/util.py
wikipedia/wikipedia.py
tc_wikipedia_lib-1.4.0.dist-info/LICENSE
tc_wikipedia_lib-1.4.0.dist-info/METADATA
tc_wikipedia_lib-1.4.0.dist-info/WHEEL
tc_wikipedia_lib-1.4.0.dist-info/top_level.txt
tc_wikipedia_lib-1.4.0.dist-info/RECORD
