Metadata-Version: 2.1
Name: tc-wikipedia-lib
Version: 1.4.0
Summary: Wikimedia API for Python
Home-page: https://github.com/polux0/Wikipedia
Author: Jonathan Goldsmith, modified by Aleksa Stojanović
Author-email: alexusnavas@gmail.com
License: MIT
Keywords: python wikimedia API
Classifier: Development Status :: 4 - Beta
Classifier: Topic :: Software Development :: Libraries
Classifier: License :: OSI Approved :: MIT License
Classifier: Programming Language :: Python
Classifier: Programming Language :: Python :: 3
License-File: LICENSE
Requires-Dist: beautifulsoup4
Requires-Dist: requests <3.0.0,>=2.0.0
